{"title": "Papyrus New Baby Card (Can't Wait)", "asin": "B08J9HVS3Z", "brand": "Papyrus", "stars": "4.9", "reviewsCount": "258 ratings", "thumbnailImage": "https://m.media-amazon.com/images/I/91wFoT8uKjL._AC_SX355_.jpg", "breadCrumbs": ["Health & Household", "\u203a", "Stationery & Gift Wrapping Supplies", "\u203a", "Gift Wrapping Supplies"], "description": "Celebrate the new arrival with this adorable Baby Congrats card from Papyrus Featuring a happy little \u201ccutie\u201d orange, rendered in light, colorful brushstrokes against a light blue sky dotted with flowers, this design is asking to be \u201cpicked\u201d A cheerful hand-lettered message on the inside lets the parent or couple know just how excited you are for them. Comes with a white envelope with gold inside flap, and gold foil seal.", "price": {"value": "6.95", "currency": "$"}, "url": "https://www.amazon.com/Papyrus-Baby-Shower-Little-Cutie/dp/B08J9HVS3Z/ref=sr_1_1636?qid=1684769367&s=arts-crafts-intl-ship&sr=1-1636"}