{"title": "Fellowes Thermal Laminating Pouches/Sheets, Letter Size 9 x 11.5-Inches, 3 mil, 100 Pack (5743301)", "asin": "B06XRJJVD4", "brand": "Fellowes", "stars": "4.7", "reviewsCount": "2,583 ratings", "thumbnailImage": "https://m.media-amazon.com/images/I/81EhO7MqeoL._AC_SY355_.jpg", "breadCrumbs": ["Office Products", "\u203a", "Office Electronics", "\u203a", "Presentation Products", "\u203a", "Laminating Supplies"], "description": "Fellowes laminating pouches are designed with quality photo safe materials providing excellent clarity and durability to preserve and protect important documents. These pouches are dry erase friendly and compatible with all thermal laminator brands.", "price": {"value": "14.99", "currency": "$"}, "url": "https://www.amazon.com/Fellowes-Thermal-Laminating-11-5-Inches-5743301/dp/B06XRJJVD4/ref=sr_1_1138?qid=1684769067&s=arts-crafts-intl-ship&sr=1-1138"}