{"title": "Munchkin\u00ae Sponge\u2122 Bottle Brush, 2 Pack, Blue", "asin": "B07DQQFP63", "brand": "Munchkin", "stars": "4.7", "reviewsCount": "42,557 ratings", "thumbnailImage": "https://m.media-amazon.com/images/I/81Tp3k8t0qL._SY355_.jpg", "breadCrumbs": ["Baby Products", "\u203a", "Feeding", "\u203a", "Bottle-Feeding", "\u203a", "Bottle Cleaning", "\u203a", "Bottle Brushes"], "description": "Washing and sanitizing your baby's bottles is a daily chore that's essential for safety and health, but it doesn't have to be a bore. Munchkin's Sponge Bottle Brush makes bottle cleaning quicker and easier, so you can spend less time at the sink and more time with your precious little one. This 2-in-1 brush is a bottle brush and nipple brush in one, so you can clean every inch of your baby bottles with just one handy tool. The sponge tip helps you reach all areas with a sudsy swipe, while the non-slip handle gives soapy hands the right grip while cleaning. The only thing dropping will be the amount of time you spend cleaning bottles. The brush base sits upright on your countertop when you're done, airing out quickly and keeping your brush off of counters.", "price": {"value": "5.47", "currency": "$"}, "url": "https://www.amazon.com/Sponge-Bottle-Brush-Pack-Blue/dp/B07DQQFP63/ref=sr_1_16?qid=1684817433&s=baby-products-intl-ship&sr=1-16"}