{"title": "Fiskars Crafts 8190 RazorEdge Fabric Shears, 9-Inch,Orange", "asin": "B00F0X2OEW", "brand": "Orange", "stars": "4.8", "reviewsCount": "780 ratings", "thumbnailImage": "https://m.media-amazon.com/images/I/71WLxiv9FQL._AC_SY741_.jpg", "breadCrumbs": ["Arts, Crafts & Sewing", "\u203a", "Crafting", "\u203a", "Craft Supplies", "\u203a", "Cutting Tools", "\u203a", "Craft Shears"], "description": "Perfect for a wide range of sewing and quilting tasks, Fiskars RazorEdge fabric Shears feature premium-grade, stainless-steel RazorEdge blades precision honed to an ultra-sharp edge to make sure every cut is crisp and clean. RazorEdge fabric Shears also offer excellent comfort and control thanks to sculpted finger and thumb loops. An advanced pivot design provides ultra-smooth cutting action, and an included sheath helps protect the blades when not in use.", "price": {"value": "22.28", "currency": "$"}, "url": "https://www.amazon.com/Fiskars-Crafts-RazorEdge-Fabric-Shears/dp/B00F0X2OEW/ref=sr_1_1113?qid=1684769055&s=arts-crafts-intl-ship&sr=1-1113"}