{"title": "Munchkin\u00ae Float & Play Bubbles\u2122 Baby and Toddler Bath Toy, 4 Count", "asin": "B00I3K25R0", "brand": "6.5 x 2.5 x 7.25 inches", "stars": "4.8", "reviewsCount": "26,276 ratings", "thumbnailImage": "https://m.media-amazon.com/images/I/71k45i-sZzL._SY355_.jpg", "breadCrumbs": ["Toys & Games", "\u203a", "Preschool", "\u203a", "Pre-Kindergarten Toys", "\u203a", "Bath Toys"], "description": "Does your little one love things that rattle, bobble, spin and shine? Then fun is sure to pop with munchkin's float and play bath bubbles. Each floating bubble has a unique center toy that rattles, bobbles, shines and spins. They are sized for little hands to hold and help teach hand eye coordination as babies learn to reach, grasp and shake the bubbles. Colorful rings move freely around the bubbles giving lots of textures and movement for your little one to explore. With these float and play bubbles, bath time fun is about to bubble up.", "price": {"value": "9.39", "currency": "$"}, "url": "https://www.amazon.com/Munchkin-Float-Play-Bubbles-Count/dp/B00I3K25R0/ref=sr_1_104?qid=1684817476&s=baby-products-intl-ship&sr=1-104"}