{"title": "Scotch Book Tape, 1.5 in x 540 in, 1 Roll/Pack, Excellent for Repairing, Reinforcing Protecting, and Covering (845-150)", "asin": "B00006IF5Q", "brand": "Scotch", "stars": "4.7", "reviewsCount": "758 ratings", "thumbnailImage": "https://m.media-amazon.com/images/I/81BSb9rzW5L._AC_SY355_.jpg", "breadCrumbs": ["Office Products", "\u203a", "Office & School Supplies", "\u203a", "Tape, Adhesives & Fasteners", "\u203a", "Tape", "\u203a", "Binding Tape"], "description": "Sukotuti Butuku TE-PU #845 38MMX13.7M", "price": {"value": "10.69", "currency": "$"}, "url": "https://www.amazon.com/3M-Scotch-Book-Inches-Yards/dp/B00006IF5Q/ref=sr_1_897?qid=1684768957&s=arts-crafts-intl-ship&sr=1-897"}