{"title": "Etekcity Infrared Thermometer Temperature Gun -58\u00b0F to 1130\u00b0F, Laser Temp IR Tool for Cooking, Grill, Pizza Oven, Griddle with Adjustable Emissivity and Max Measure with Color LCD Screen Black", "asin": "B0BGX95FF4", "brand": "Etekcity", "stars": "4.5", "reviewsCount": "5,891 ratings", "thumbnailImage": "https://m.media-amazon.com/images/I/613o0my+OrL._SX342_.jpg", "breadCrumbs": ["Industrial & Scientific", "\u203a", "Test, Measure & Inspect", "\u203a", "Temperature & Humidity", "\u203a", "Thermometers", "\u203a", "Digital Thermometers"], "description": "Etekcity Lasergrip 1260", "price": {"value": "19.79", "currency": "$"}, "url": "https://www.amazon.com/Etekcity-Infrared-Thermometer-Temperature-Adjustable/dp/B0BGX95FF4/ref=sr_1_86?qid=1684811453&s=automotive-intl-ship&sr=1-86"}