{"title": "VIDBOX Stopmotion Studio 4.0", "asin": "June 10, 2013", "brand": "4.0", "stars": "2.8", "reviewsCount": "29 ratings", "thumbnailImage": "https://m.media-amazon.com/images/I/71xX06G4ZGL._AC_SX466_.jpg", "breadCrumbs": ["Software", "\u203a", "Children's", "\u203a", "Art & Creativity"], "description": "Capture images using webcam, camcorder and DSLR cameras. Using the adjustable frame rate, you can control the speed of your video. The Chroma Key effect allows you to easily change the background to create the best setting for your subject using a blue/green screen. In addition, auto capture, grid, and rotoscope features help users create more flowing movements with ease. Improved Storyboard for Easy Editing. The storyboard allows users to view the frames in sequence for easy editing, and users can add on screen text, subtitles, sound effect, voice, and background music. Use the Full Storyboard tool to see a larger view of your captured frames, and re arrange the order of the frames with your mouse via drag and drop. Various Enhancements. The new DSLR camera support allows you to create stunning 1080p HD video using Canon/Nikon DSLR cameras with Live View support. The String Removal, Image Editor and Overlay Frames tool can help you add special effects and create amazing stop motion animation.", "price": {"value": "66.65", "currency": "$"}, "url": "https://www.amazon.com/VIDBOX-4-0-Stopmotion-Studio/dp/B00DFU0ZFW/ref=sr_1_179?qid=1685339161&s=software-intl-ship&sr=1-179"}